AUTHORS
LICENSE
MANIFEST.in
setup.py
django_sortable_fc.egg-info/PKG-INFO
django_sortable_fc.egg-info/SOURCES.txt
django_sortable_fc.egg-info/dependency_links.txt
django_sortable_fc.egg-info/not-zip-safe
django_sortable_fc.egg-info/top_level.txt
sortable/__init__.py
sortable/admin.py
sortable/models.py
sortable/static/js/django-admin-sortable.js