Metadata-Version: 1.0
Name: django-sortable-fc
Version: 1.0
Summary: An app to add drag-and-drop to admin to reorder instances of models.
Home-page: http://github.com/futurecolors/django-sortable/
Author: Red Interactive Agency
Author-email: geeks@ff0000.com
License: UNKNOWN
Platform: UNKNOWN
Classifier: Development Status :: 3 - Alpha
Classifier: Environment :: Web Environment
Classifier: Intended Audience :: Developers
Classifier: License :: OSI Approved :: BSD License
Classifier: Operating System :: OS Independent
Classifier: Programming Language :: Python
Classifier: Framework :: Django
